Metadata-Version: 2.1
Name: mkvsubmerge
Version: 0.0.4
Summary: Setuptools setup.py for mkvsubmerge.
Home-page: https://github.com/medopaw/mkvsubmerge
Author: Med0paW
Author-email: medopaw@gmail.com
License: MIT
Platform: UNKNOWN
Classifier: Development Status :: 3 - Alpha
Classifier: License :: OSI Approved :: MIT License
Classifier: Environment :: Console
Classifier: Natural Language :: English
Classifier: Operating System :: OS Independent
Classifier: Programming Language :: Python :: 3
Classifier: Topic :: Software Development
Classifier: Topic :: Utilities
